odoo/addons/web_font_size_report_layout/README.rst
odoo/addons/web_font_size_report_layout/__init__.py
odoo/addons/web_font_size_report_layout/__manifest__.py
odoo/addons/web_font_size_report_layout/i18n/it.po
odoo/addons/web_font_size_report_layout/i18n/web_font_size_report_layout.pot
odoo/addons/web_font_size_report_layout/models/__init__.py
odoo/addons/web_font_size_report_layout/models/base_document_layout.py
odoo/addons/web_font_size_report_layout/models/res_company.py
odoo/addons/web_font_size_report_layout/readme/CONTRIBUTORS.md
odoo/addons/web_font_size_report_layout/readme/DESCRIPTION.md
odoo/addons/web_font_size_report_layout/readme/INSTALL.md
odoo/addons/web_font_size_report_layout/readme/USAGE.md
odoo/addons/web_font_size_report_layout/static/description/icon.png
odoo/addons/web_font_size_report_layout/static/description/index.html
odoo/addons/web_font_size_report_layout/static/src/scss/report_font_size.scss
odoo/addons/web_font_size_report_layout/tests/__init__.py
odoo/addons/web_font_size_report_layout/tests/test_company_font_size.py
odoo/addons/web_font_size_report_layout/tests/test_document_layout_onchange.py
odoo/addons/web_font_size_report_layout/views/base_document_layout_views.xml
odoo/addons/web_font_size_report_layout/views/report_templates_inherit.xml
odoo_addon_web_font_size_report_layout-16.0.1.1.0.4.dist-info/METADATA
odoo_addon_web_font_size_report_layout-16.0.1.1.0.4.dist-info/WHEEL
odoo_addon_web_font_size_report_layout-16.0.1.1.0.4.dist-info/top_level.txt
odoo_addon_web_font_size_report_layout-16.0.1.1.0.4.dist-info/RECORD
