Metadata-Version: 2.1
Name: odoo-addon-web_font_size_report_layout
Version: 16.0.1.1.0.4
Requires-Python: >=3.10
Requires-Dist: odoo>=16.0a,<16.1dev
Summary: Adds a font size selector (pt) to the Document Layout wizard
Home-page: https://github.com/OCA/web
License: LGPL-3
Author: Binhex,Odoo Community Association (OCA)
Author-email: support@odoo-community.org
Classifier: Programming Language :: Python
Classifier: Framework :: Odoo
Classifier: Framework :: Odoo :: 16.0
Classifier: License :: OSI Approved :: GNU Lesser General Public License v3 (LGPLv3)
